mplhep/__init__.py
mplhep/_compat.py
mplhep/_deprecate.py
mplhep/_tools.py
mplhep/_version.py
mplhep/_version.pyi
mplhep/alice.py
mplhep/atlas.py
mplhep/cms.py
mplhep/comparison.py
mplhep/error_estimation.py
mplhep/label.py
mplhep/lhcb.py
mplhep/plot.py
mplhep/utils.py
mplhep/styles/__init__.py
mplhep/styles/alice.py
mplhep/styles/atlas.py
mplhep/styles/cms.py
mplhep/styles/lhcb.py
mplhep/styles/plothist.py
mplhep-0.4.0.dist-info/METADATA
mplhep-0.4.0.dist-info/WHEEL
mplhep-0.4.0.dist-info/licenses/LICENSE
mplhep-0.4.0.dist-info/RECORD
