Metadata-Version: 2.4
Name: mplhep
Version: 0.4.0
Summary: Matplotlib styles for HEP
Project-URL: Homepage, https://github.com/scikit-hep/mplhep
Author-email: andrzejnovak <novak5andrzej@gmail.com>
License-Expression: MIT
License-File: LICENSE
Classifier: Framework :: Matplotlib
Classifier: Intended Audience :: Science/Research
Classifier: License :: OSI Approved :: MIT License
Classifier: Programming Language :: Python :: 3
Classifier: Programming Language :: Python :: 3 :: Only
Classifier: Programming Language :: Python :: 3.8
Classifier: Programming Language :: Python :: 3.9
Classifier: Programming Language :: Python :: 3.10
Classifier: Programming Language :: Python :: 3.11
Classifier: Programming Language :: Python :: 3.12
Classifier: Programming Language :: Python :: 3.13
Classifier: Topic :: Scientific/Engineering :: Physics
Requires-Python: >=3.8
Requires-Dist: matplotlib>=3.4
Requires-Dist: mplhep-data>=0.0.4
Requires-Dist: numpy>=1.16.0
Requires-Dist: packaging
Requires-Dist: uhi>=0.2.0
Provides-Extra: all
Requires-Dist: boost-histogram; extra == 'all'
Requires-Dist: bumpversion; extra == 'all'
Requires-Dist: hist; extra == 'all'
Requires-Dist: jupyter; extra == 'all'
Requires-Dist: pre-commit; extra == 'all'
Requires-Dist: pytest-mock; extra == 'all'
Requires-Dist: pytest-mpl; extra == 'all'
Requires-Dist: pytest-xdist; extra == 'all'
Requires-Dist: pytest>=6.0; extra == 'all'
Requires-Dist: scikit-hep-testdata; extra == 'all'
Requires-Dist: scipy>=1.1.0; extra == 'all'
Requires-Dist: twine; extra == 'all'
Requires-Dist: uproot; extra == 'all'
Requires-Dist: uproot4; extra == 'all'
Provides-Extra: dev
Requires-Dist: bumpversion; extra == 'dev'
Requires-Dist: jupyter; extra == 'dev'
Requires-Dist: pre-commit; extra == 'dev'
Requires-Dist: twine; extra == 'dev'
Provides-Extra: test
Requires-Dist: boost-histogram; extra == 'test'
Requires-Dist: hist; extra == 'test'
Requires-Dist: pytest-mock; extra == 'test'
Requires-Dist: pytest-mpl; extra == 'test'
Requires-Dist: pytest-xdist; extra == 'test'
Requires-Dist: pytest>=6.0; extra == 'test'
Requires-Dist: scikit-hep-testdata; extra == 'test'
Requires-Dist: scipy>=1.1.0; extra == 'test'
Requires-Dist: uproot; extra == 'test'
Requires-Dist: uproot4; extra == 'test'
